{
  "Version": "1.13",
  "AppendixRelease": "K",
  "Properties": [
    {
      "Name": "動作状態",
      "Code": "0x80",
      "Detail": "ON／OFF の状態を示す。",
      "Value": "ＯＮ＝0x30，ＯＦＦ＝0x31",
      "DataType": "unsigned char",
      "LogicalDataType": "byte",
      "MinSize": 1,
      "MaxSize": 1,
      "Get": true,
      "GetRequired": true,
      "Set": true,
      "SetRequired": false,
      "Anno": true,
      "AnnoRequired": false,
      "Description": "",
      "Unit": "－"
    },
    {
      "Name": "検知閾値レベル設定",
      "Code": "0xB0",
      "Detail": "レベルを８段階で指定。",
      "Value": "0x31～0x38",
      "DataType": "unsigned char",
      "LogicalDataType": "byte",
      "MinSize": 1,
      "MaxSize": 1,
      "Get": true,
      "GetRequired": false,
      "Set": true,
      "SetRequired": false,
      "Anno": false,
      "AnnoRequired": false,
      "Description": "",
      "Unit": "－"
    },
    {
      "Name": "空気汚染検出状態",
      "Code": "0xB1",
      "Detail": "空気汚染の検出状況を示す。",
      "Value": "空気汚染検出有＝0x41，空気汚染検出無＝0x42",
      "DataType": "unsigned char",
      "LogicalDataType": "byte",
      "MinSize": 1,
      "MaxSize": 1,
      "Get": true,
      "GetRequired": true,
      "Set": false,
      "SetRequired": false,
      "Anno": true,
      "AnnoRequired": false,
      "Description": "",
      "Unit": "－"
    }
  ]
}